ilias2nbgrader/__init__.py
ilias2nbgrader/converters/__init__.py
ilias2nbgrader/converters/converter.py
ilias2nbgrader/converters/feedbackconverter.py
ilias2nbgrader/converters/groupfeedbackconverter.py
ilias2nbgrader/converters/groupsubmissionconverter.py
ilias2nbgrader/converters/submissionconverter.py
ilias2nbgrader/preprocessors/__init__.py
ilias2nbgrader/preprocessors/addextrafiles.py
ilias2nbgrader/preprocessors/copyfeedback.py
ilias2nbgrader/preprocessors/copygroupfeedback.py
ilias2nbgrader/preprocessors/createfolderstructure.py
ilias2nbgrader/preprocessors/deletetempfolders.py
ilias2nbgrader/preprocessors/extract.py
ilias2nbgrader/preprocessors/extractassignmentinfo.py
ilias2nbgrader/preprocessors/extractfeedback.py
ilias2nbgrader/preprocessors/extractsinglesubmission.py
ilias2nbgrader/preprocessors/groupsubmissions.py
ilias2nbgrader/preprocessors/movetosubmitted.py
ilias2nbgrader/preprocessors/preprocessor.py
ilias2nbgrader/preprocessors/renamenotebooks.py
ilias2nbgrader/preprocessors/renamesubmission.py
ilias2nbgrader/preprocessors/restructuresubmission.py
ilias2nbgrader/preprocessors/zipfeedback.py
ilias2nbgrader/tests/__init__.py
ilias2nbgrader/tests/preprocessors/__init__.py
ilias2nbgrader/tests/preprocessors/base.py
ilias2nbgrader/tests/preprocessors/groupbase.py
ilias2nbgrader/tests/preprocessors/test_addextrafiles.py
ilias2nbgrader/tests/preprocessors/test_copyfeedback.py
ilias2nbgrader/tests/preprocessors/test_copygroupfeedback.py
ilias2nbgrader/tests/preprocessors/test_createfolderstructure.py
ilias2nbgrader/tests/preprocessors/test_deletetempfolders.py
ilias2nbgrader/tests/preprocessors/test_extract.py
ilias2nbgrader/tests/preprocessors/test_extractassignmentinfo.py
ilias2nbgrader/tests/preprocessors/test_extractfeedback.py
ilias2nbgrader/tests/preprocessors/test_extractsinglesubmission.py
ilias2nbgrader/tests/preprocessors/test_groupsubmissions.py
ilias2nbgrader/tests/preprocessors/test_movetosubmitted.py
ilias2nbgrader-0.4.3.dist-info/LICENSE
ilias2nbgrader-0.4.3.dist-info/METADATA
ilias2nbgrader-0.4.3.dist-info/WHEEL
ilias2nbgrader-0.4.3.dist-info/top_level.txt
ilias2nbgrader-0.4.3.dist-info/RECORD
