Metadata-Version: 2.1
Name: ilias2nbgrader
Version: 0.4.3
Summary: Exchange submissions and feedbacks between ILIAS and nbgrader
Home-page: https://github.com/DigiKlausur/ilias2nbgrader
Author: Tim Metzler
Author-email: tim.metzler@h-brs.de
License: MIT
Platform: UNKNOWN
Requires-Dist: rapidfuzz
Requires-Dist: nbformat
